LICENSE
MANIFEST.in
README.md
deep_throat.py
setup.py
deep_throat.egg-info/PKG-INFO
deep_throat.egg-info/SOURCES.txt
deep_throat.egg-info/dependency_links.txt
deep_throat.egg-info/entry_points.txt
deep_throat.egg-info/requires.txt
deep_throat.egg-info/top_level.txt