Metadata-Version: 1.0
Name: deep-throat
Version: 2016.11.25.50
Summary: speech
Home-page: https://github.com/wdbm/deep_throat
Author: Will Breaden Madden
Author-email: wbm@protonmail.ch
License: GPLv3
Platform: UNKNOWN
